omniconverter/__init__.py
omniconverter/cli.py
omniconverter/omniconverter.py
omniconverter/read_stata.py
omniconverter/read_tdp.py
omniconverter/stata_to_statistics.py
omniconverter/write_stata.py
omniconverter/write_stats.py
omniconverter/write_tdp.py
omniconverter-0.1.7.dist-info/METADATA
omniconverter-0.1.7.dist-info/RECORD
omniconverter-0.1.7.dist-info/WHEEL
omniconverter-0.1.7.dist-info/entry_points.txt
omniconverter-0.1.7.dist-info/top_level.txt
