Metadata-Version: 2.1
Name: omniconverter
Version: 0.1.7
Summary: Convert file types
Home-page: https://github.com/mpahl/omniconverter
Author: Marius Pahl
Author-email: marius.jf.pahl@gmail.com
License: MIT license
Keywords: omniconverter
Platform: UNKNOWN
Classifier: Development Status :: 2 - Pre-Alpha
Classifier: Intended Audience :: Developers
Classifier: License :: OSI Approved :: MIT License
Classifier: Natural Language :: English
Classifier: Programming Language :: Python :: 3
Classifier: Programming Language :: Python :: 3.4
Classifier: Programming Language :: Python :: 3.5
Classifier: Programming Language :: Python :: 3.6
Classifier: Programming Language :: Python :: 3.7
Requires-Dist: Click (>=6.0)
